eventweave/__init__.py
eventweave/py.typed
eventweave-0.5.0.dist-info/LICENSE
eventweave-0.5.0.dist-info/METADATA
eventweave-0.5.0.dist-info/WHEEL
eventweave-0.5.0.dist-info/RECORD
