Metadata-Version: 2.3
Name: eventweave
Version: 0.5.0
Summary: Weave multiple streams of intervals into combinations
Author: Max Görner
Author-email: 5477952+MaxG87@users.noreply.github.com
Requires-Python: >=3.10
Classifier: Programming Language :: Python :: 3
Classifier: Programming Language :: Python :: 3.10
Classifier: Programming Language :: Python :: 3.11
Classifier: Programming Language :: Python :: 3.12
Classifier: Programming Language :: Python :: 3.13
Project-URL: Changelog, https://github.com/MaxG87/eventweave/blob/main/CHANGELOG.md
Project-URL: Homepage, https://github.com/MaxG87/eventweave
Project-URL: Issues, https://github.com/MaxG87/eventweave
Project-URL: Repository, https://github.com/MaxG87/eventweave
